setup.py
formatstring/__init__.py
formatstring/architectures.py
formatstring/pattern.py
formatstring/pattern_create.py
formatstring/pattern_offset.py
formatstring/payloads.py
formatstring.egg-info/PKG-INFO
formatstring.egg-info/SOURCES.txt
formatstring.egg-info/dependency_links.txt
formatstring.egg-info/entry_points.txt
formatstring.egg-info/requires.txt
formatstring.egg-info/top_level.txt