Metadata-Version: 1.1
Name: formatstring
Version: 1.1
Summary: Format string exploitation helper
Home-page: https://github.com/arthaud/formatstring
Author: Maxime Arthaud
Author-email: maxime@arthaud.me
License: MIT
Keywords: format string security exploit payload vulnerability ctf
Platform: UNKNOWN
Classifier: Development Status :: 5 - Production/Stable
Classifier: License :: OSI Approved :: MIT License
Classifier: Topic :: Security
